exantedata_api/__init__.py
exantedata_api/exantedata_api.py
exantedata_api-3.0.0.dist-info/METADATA
exantedata_api-3.0.0.dist-info/WHEEL
exantedata_api-3.0.0.dist-info/top_level.txt
exantedata_api-3.0.0.dist-info/RECORD
