Metadata-Version: 2.1
Name: exantedata-api
Version: 3.0.0
Summary: ExanteData API python library
Author: tech@exantedata.com
Requires-Dist: pandas
Requires-Dist: requests
